{
  "website": "https://www.medifocalmarketing.com/home",
  "sitemap_url": "https://www.medifocalmarketing.com/sitemap.xml",
  "robots_txt_url": "https://www.medifocalmarketing.com/robots.txt",
  "verification_method": "HTML_TAG",
  "verification_code": "zXCqsBo-am05DJr4nrfuRWajuYKztxLykdwdMvFceLM",
  "analytics_tracking_id": "G-D5E0PMJHP6",
  "target_keywords": [
    "web design Sydney",
    "web design Newcastle", 
    "digital marketing Sydney",
    "SEO services Newcastle",
    "eCommerce development Sydney",
    "Shopify developer Sydney",
    "WooCommerce Newcastle",
    "custom software Sydney",
    "business automation Newcastle",
    "UI UX design Sydney"
  ],
  "local_seo": {
    "business_name": "Medifocal Marketing",
    "primary_location": "Sydney, NSW, Australia",
    "secondary_location": "Newcastle, NSW, Australia",
    "business_category": "Digital Marketing Agency",
    "services": [
      "Web Design",
      "SEO Services", 
      "E-commerce Development",
      "Custom Software",
      "Business Automation",
      "UI/UX Design",
      "Digital Marketing"
    ]
  },
  "structured_data_types": [
    "Organization",
    "ProfessionalService", 
    "FAQPage",
    "BreadcrumbList",
    "WebSite",
    "LocalBusiness"
  ],
  "pages_to_index": [
    "https://www.medifocalmarketing.com/home"
  ],
  "internal_sections": [
    "ui-ux-page",
    "seo-page", 
    "website-design-page",
    "web-apps-page",
    "ecommerce-page",
    "business-automation-page",
    "pricing-page",
    "contact-page",
    "shopify-page",
    "woocommerce-page",
    "custom-software-page",
    "saas-development-page",
    "crm-erp-page",
    "hosting-support-page",
    "ai-setup-page",
    "dashboards-analytics-page",
    "data-strategy-page"
  ],
  "monitoring_setup": {
    "google_analytics": {
      "enabled": true,
      "tracking_id": "G-D5E0PMJHP6",
      "goals": [
        "contact_form_submission",
        "service_page_views",
        "pricing_page_views"
      ]
    },
    "google_search_console": {
      "enabled": true,
      "verification_complete": false,
      "sitemap_submitted": false,
      "indexing_requested": false
    }
  },
  "seo_checklist": {
    "technical_seo": {
      "sitemap_created": true,
      "robots_txt_created": true,
      "canonical_urls": true,
      "meta_descriptions": true,
      "structured_data": true,
      "mobile_responsive": true,
      "page_speed_optimized": true
    },
    "content_seo": {
      "target_keywords_identified": true,
      "local_keywords_targeted": true,
      "service_pages_optimized": true,
      "contact_information_visible": true
    },
    "local_seo": {
      "google_my_business_setup": false,
      "nap_consistency": false,
      "local_citations": false,
      "customer_reviews": false
    }
  }
}
